psd_export/__init__.py
psd_export/blendfuncs_float.c
psd_export/blendfuncs_float.cpython-313-x86_64-linux-gnu.so
psd_export/blendfuncs_float.pyx
psd_export/blendfuncs_short.c
psd_export/blendfuncs_short.cpython-313-x86_64-linux-gnu.so
psd_export/blendfuncs_short.pyx
psd_export/composite.py
psd_export/export.py
psd_export/filters.py
psd_export/rle.c
psd_export/rle.cpython-313-x86_64-linux-gnu.so
psd_export/rle.pyx
psd_export/util.py
psd_export-1.0.36.dist-info/METADATA
psd_export-1.0.36.dist-info/WHEEL
psd_export-1.0.36.dist-info/entry_points.txt
psd_export-1.0.36.dist-info/top_level.txt
psd_export-1.0.36.dist-info/RECORD
psd_export-1.0.36.dist-info/licenses/LICENSE
