Metadata-Version: 2.4
Name: psd-export
Version: 1.0.36
Summary: Fast exporting of PSDs with [tagged] layers for variants.
Author: cromachina
License-Expression: GPL-3.0-or-later
Project-URL: Homepage, https://github.com/cromachina/psd-export
Keywords: exporter,psd,art
Classifier: Intended Audience :: End Users/Desktop
Classifier: Programming Language :: Python
Classifier: Programming Language :: Python :: 3 :: Only
Classifier: Topic :: Artistic Software
Classifier: Topic :: Multimedia :: Graphics
Classifier: Topic :: Multimedia :: Graphics :: Graphics Conversion
Requires-Python: >=3.13
License-File: LICENSE
Requires-Dist: numpy
Requires-Dist: opencv_python
Requires-Dist: psd_tools
Requires-Dist: psutil
Requires-Dist: pyrsistent
Dynamic: license-file
